ecidcodes/CMakeLists.txt
ecidcodes/README.md
ecidcodes/__init__.py
ecidcodes/_abi3_dummy.abi3.so
ecidcodes/idcodes.cpython-39-x86_64-linux-gnu.so
ecidcodes/idcodes_gf.cpython-39-x86_64-linux-gnu.so
ecidcodes/idcodes_pmhid.cpython-39-x86_64-linux-gnu.so
ecidcodes/idcodes_rmid.cpython-39-x86_64-linux-gnu.so
ecidcodes/idcodes_rs2id.cpython-39-x86_64-linux-gnu.so
ecidcodes/idcodes_rsid.cpython-39-x86_64-linux-gnu.so
ecidcodes/idcodes_sha1id.cpython-39-x86_64-linux-gnu.so
ecidcodes/idcodes_sha256id.cpython-39-x86_64-linux-gnu.so
ecidcodes/pybind_idcodes.cpp
ecidcodes/requirements.txt
ecidcodes/version
ecidcodes/encoder/gf/gf.cpp
ecidcodes/encoder/pmhid/pmhid.cpp
ecidcodes/encoder/rmid/rmid.cpp
ecidcodes/encoder/rs2id/rs2id.cpp
ecidcodes/encoder/rsid/rsid.cpp
ecidcodes/encoder/sha1id/sha1id.cpp
ecidcodes/encoder/sha256id/sha256id.cpp
ecidcodes-0.2.8.dist-info/licenses/LICENSE
ecidcodes-0.2.8.dist-info/METADATA
ecidcodes-0.2.8.dist-info/WHEEL
ecidcodes-0.2.8.dist-info/top_level.txt
ecidcodes-0.2.8.dist-info/RECORD
